Metadata-Version: 2.4
Name: glotlib
Version: 1.0.3
Summary: Library for creating plots using OpenGL.
Home-page: https://github.com/tgree/glotlib
Author: Terry Greeniaus
Author-email: terry.greeniaus@gmail.com
License: LGPLv2
Keywords: glotlib
Classifier: Operating System :: OS Independent
Classifier: Programming Language :: Python :: 3
Classifier: License :: OSI Approved :: GNU Lesser General Public License v2 (LGPLv2)
Requires-Python: >=3.7
License-File: LICENSE
Requires-Dist: freetype-py
Requires-Dist: glfw
Requires-Dist: PyOpenGL
Dynamic: license-file
